LICENSE
MANIFEST.in
README.md
pyproject.toml
setup.py
cpp/rasterizer_cuda.cu
cpp/rasterizer_kernels.cu
cpp/rasterizer_kernels.cuh
cpp/rasterizer_python.cpp
cpp/rasterizer_torch.cu
cpp/ds_cuda_rasterizer/rasterizer_cuda.hpp
cpp/ds_cuda_rasterizer/rasterizer_torch.hpp
cpp/gsplat/backward.cu
cpp/gsplat/backward.cuh
cpp/gsplat/bindings.cu
cpp/gsplat/bindings.h
cpp/gsplat/config.h
cpp/gsplat/helpers.cuh
cpp/gsplat/sh.cuh
cpp/gsplat/third_party/glm/.git
cpp/gsplat/third_party/glm/.gitignore
cpp/gsplat/third_party/glm/CMakeLists.txt
cpp/gsplat/third_party/glm/copying.txt
cpp/gsplat/third_party/glm/manual.md
cpp/gsplat/third_party/glm/readme.md
cpp/gsplat/third_party/glm/.github/workflows/ci.yml
cpp/gsplat/third_party/glm/.github/workflows/make_light_release.yml
cpp/gsplat/third_party/glm/cmake/cmake_uninstall.cmake.in
cpp/gsplat/third_party/glm/doc/man.doxy
cpp/gsplat/third_party/glm/doc/manual.pdf
cpp/gsplat/third_party/glm/doc/api/a00002.html
cpp/gsplat/third_party/glm/doc/api/a00002_source.html
cpp/gsplat/third_party/glm/doc/api/a00005_source.html
cpp/gsplat/third_party/glm/doc/api/a00008_source.html
cpp/gsplat/third_party/glm/doc/api/a00011_source.html
cpp/gsplat/third_party/glm/doc/api/a00014_source.html
cpp/gsplat/third_party/glm/doc/api/a00017_source.html
cpp/gsplat/third_party/glm/doc/api/a00020_source.html
cpp/gsplat/third_party/glm/doc/api/a00023_source.html
cpp/gsplat/third_party/glm/doc/api/a00026_source.html
cpp/gsplat/third_party/glm/doc/api/a00029_source.html
cpp/gsplat/third_party/glm/doc/api/a00032_source.html
cpp/gsplat/third_party/glm/doc/api/a00035_source.html
cpp/gsplat/third_party/glm/doc/api/a00038_source.html
cpp/gsplat/third_party/glm/doc/api/a00041.html
cpp/gsplat/third_party/glm/doc/api/a00041_source.html
cpp/gsplat/third_party/glm/doc/api/a00044.html
cpp/gsplat/third_party/glm/doc/api/a00044_source.html
cpp/gsplat/third_party/glm/doc/api/a00047.html
cpp/gsplat/third_party/glm/doc/api/a00047_source.html
ds_splat.egg-info/PKG-INFO
ds_splat.egg-info/SOURCES.txt
ds_splat.egg-info/dependency_links.txt
ds_splat.egg-info/requires.txt
ds_splat.egg-info/top_level.txt