Metadata-Version: 2.1
Name: ds-splat
Version: 0.0.1
Summary: A CUDA-based gaussian splatting rasterizer extension for PyTorch.
Author-email: "deepsense.ai" <contact@deepsense.ai>
Keywords: pytorch,cuda,rasterizer,deep learning
Classifier: Programming Language :: Python :: 3
Classifier: License :: OSI Approved :: MIT License
Classifier: Operating System :: OS Independent
Requires-Python: >=3.7
License-File: LICENSE
Provides-Extra: test
Requires-Dist: torch; extra == "test"
